{
  "palette": [
    {
      "key": "sepia",
      "scheme": "dark",
      "hexCode": "AF8C6A",
      "r": 0.6850000023841858,
      "g": 0.550000011920929,
      "b": 0.41499999165534973,
      "a": 1
    },
    {
      "key": "sepia",
      "scheme": "light",
      "hexCode": "957350",
      "r": 0.5849999785423279,
      "g": 0.44999998807907104,
      "b": 0.3149999976158142,
      "a": 1
    },
    {
      "key": "gray",
      "scheme": "dark",
      "hexCode": "B2BBCC",
      "r": 0.699999988079071,
      "g": 0.7333335876464844,
      "b": 0.800000011920929,
      "a": 1
    },
    {
      "key": "gray",
      "scheme": "light",
      "hexCode": "667799",
      "r": 0.4000000059604645,
      "g": 0.46666666865348816,
      "b": 0.6000000238418579,
      "a": 1
    },
    {
      "key": "blue",
      "scheme": "dark",
      "hexCode": "5781FF",
      "r": 0.3400000035762787,
      "g": 0.5049999952316284,
      "b": 1,
      "a": 1
    },
    {
      "key": "blue",
      "scheme": "light",
      "hexCode": "3661E2",
      "r": 0.21250002086162567,
      "g": 0.3812499940395355,
      "b": 0.887499988079071,
      "a": 1
    },
    {
      "key": "sky blue",
      "scheme": "dark",
      "hexCode": "2BADEE",
      "r": 0.16749998927116394,
      "g": 0.6775000095367432,
      "b": 0.9325000047683716,
      "a": 1
    },
    {
      "key": "sky blue",
      "scheme": "light",
      "hexCode": "189CDC",
      "r": 0.09599999338388443,
      "g": 0.6103485822677612,
      "b": 0.8640000224113464,
      "a": 1
    },
    {
      "key": "mint",
      "scheme": "dark",
      "hexCode": "0AC2A3",
      "r": 0.04000000283122063,
      "g": 0.7600000500679016,
      "b": 0.64000004529953,
      "a": 1
    },
    {
      "key": "mint",
      "scheme": "light",
      "hexCode": "13AE95",
      "r": 0.07599999010562897,
      "g": 0.6840000152587891,
      "b": 0.5826666355133057,
      "a": 1
    },
    {
      "key": "green",
      "scheme": "dark",
      "hexCode": "66C653",
      "r": 0.40000006556510925,
      "g": 0.7749999761581421,
      "b": 0.32500001788139343,
      "a": 1
    },
    {
      "key": "green",
      "scheme": "light",
      "hexCode": "49B234",
      "r": 0.2850000262260437,
      "g": 0.6974999904632568,
      "b": 0.20250000059604645,
      "a": 1
    },
    {
      "key": "yellow",
      "scheme": "dark",
      "hexCode": "EEBD2B",
      "r": 0.9325000047683716,
      "g": 0.7412499189376831,
      "b": 0.16750003397464752,
      "a": 1
    },
    {
      "key": "yellow",
      "scheme": "light",
      "hexCode": "C7A705",
      "r": 0.7799999713897705,
      "g": 0.6533333659172058,
      "b": 0.019999999552965164,
      "a": 1
    },
    {
      "key": "orange",
      "scheme": "dark",
      "hexCode": "EF8234",
      "r": 0.9355000257492065,
      "g": 0.5090832114219666,
      "b": 0.2044999897480011,
      "a": 1
    },
    {
      "key": "orange",
      "scheme": "light",
      "hexCode": "E56E19",
      "r": 0.8977500200271606,
      "g": 0.43224987387657166,
      "b": 0.09975000470876694,
      "a": 1
    },
    {
      "key": "red",
      "scheme": "dark",
      "hexCode": "F1505E",
      "r": 0.9445000290870667,
      "g": 0.3154999911785126,
      "b": 0.36791670322418213,
      "a": 1
    },
    {
      "key": "red",
      "scheme": "light",
      "hexCode": "DD3C49",
      "r": 0.8650000095367432,
      "g": 0.23499996960163116,
      "b": 0.2874999940395355,
      "a": 1
    },
    {
      "key": "pink",
      "scheme": "dark",
      "hexCode": "E963BC",
      "r": 0.9125000238418579,
      "g": 0.38749998807907104,
      "b": 0.7374999523162842,
      "a": 1
    },
    {
      "key": "pink",
      "scheme": "light",
      "hexCode": "E54DB2",
      "r": 0.8999999761581421,
      "g": 0.30000001192092896,
      "b": 0.6999999284744263,
      "a": 1
    },
    {
      "key": "purple",
      "scheme": "dark",
      "hexCode": "AB57FF",
      "r": 0.6700000166893005,
      "g": 0.3400000035762787,
      "b": 1,
      "a": 1
    },
    {
      "key": "purple",
      "scheme": "light",
      "hexCode": "7F4DE5",
      "r": 0.49999985098838806,
      "g": 0.30000004172325134,
      "b": 0.8999999761581421,
      "a": 1
    },
    {
      "key": "accessory",
      "scheme": "dark",
      "hexCode": "928E87",
      "r": 0.5724999904632568,
      "g": 0.5575000047683716,
      "b": 0.5275000333786011,
      "a": 1
    },
    {
      "key": "accessory",
      "scheme": "light",
      "hexCode": "A39C8F",
      "r": 0.6399999856948853,
      "g": 0.6133333444595337,
      "b": 0.5600000023841858,
      "a": 1
    },
    {
      "key": "tertiary body",
      "scheme": "dark",
      "hexCode": "AAA7A1",
      "r": 0.6675000190734863,
      "g": 0.65583336353302,
      "b": 0.6324999928474426,
      "a": 1
    },
    {
      "key": "tertiary body",
      "scheme": "light",
      "hexCode": "8C8473",
      "r": 0.550000011920929,
      "g": 0.5166667103767395,
      "b": 0.45000001788139343,
      "a": 1
    },
    {
      "key": "secondary body",
      "scheme": "dark",
      "hexCode": "CFCDC9",
      "r": 0.8100000023841858,
      "g": 0.8033333420753479,
      "b": 0.7900000214576721,
      "a": 1
    },
    {
      "key": "secondary body",
      "scheme": "light",
      "hexCode": "625C50",
      "r": 0.38499999046325684,
      "g": 0.3616666793823242,
      "b": 0.3149999976158142,
      "a": 1
    },
    {
      "key": "body",
      "scheme": "dark",
      "hexCode": "F3F2F2",
      "r": 0.9526315927505493,
      "g": 0.9508771896362305,
      "b": 0.9473684430122375,
      "a": 1
    },
    {
      "key": "body",
      "scheme": "light",
      "hexCode": "38352E",
      "r": 0.2199999839067459,
      "g": 0.20666666328907013,
      "b": 0.18000000715255737,
      "a": 1
    },
    {
      "key": "tertiary background",
      "scheme": "dark",
      "hexCode": "000000",
      "r": 0,
      "g": 0,
      "b": 0,
      "a": 1
    },
    {
      "key": "tertiary background",
      "scheme": "light",
      "hexCode": "E3E1DD",
      "r": 0.8920000195503235,
      "g": 0.8840000033378601,
      "b": 0.8679999709129333,
      "a": 1
    },
    {
      "key": "secondary background",
      "scheme": "dark",
      "hexCode": "151513",
      "r": 0.08393442630767822,
      "g": 0.08131147176027298,
      "b": 0.07606557011604309,
      "a": 1
    },
    {
      "key": "secondary background",
      "scheme": "light",
      "hexCode": "F1F0EE",
      "r": 0.9459999799728394,
      "g": 0.9420000314712524,
      "b": 0.9340000152587891,
      "a": 1
    },
    {
      "key": "background",
      "scheme": "dark",
      "hexCode": "2B2927",
      "r": 0.1679999977350235,
      "g": 0.1626666635274887,
      "b": 0.15199999511241913,
      "a": 1
    },
    {
      "key": "background",
      "scheme": "light",
      "hexCode": "FFFFFF",
      "r": 1,
      "g": 1,
      "b": 1,
      "a": 1
    }
  ],
  "typography": [
    {
      "key": "h1",
      "fontFamily": "Inter Medium",
      "fontPostScriptName": "Inter-Medium",
      "fontWeight": 500,
      "fontSize": 48,
      "letterSpacing": 0,
      "lineHeight": 100,
      "isItalic": false
    },
    {
      "key": "h2",
      "fontFamily": "Inter Medium",
      "fontPostScriptName": "Inter-Medium",
      "fontWeight": 500,
      "fontSize": 40,
      "letterSpacing": 0,
      "lineHeight": 100,
      "isItalic": false
    },
    {
      "key": "h3",
      "fontFamily": "Inter Medium",
      "fontPostScriptName": "Inter-Medium",
      "fontWeight": 500,
      "fontSize": 32,
      "letterSpacing": 0,
      "lineHeight": 100,
      "isItalic": false
    },
    {
      "key": "h4",
      "fontFamily": "Inter Medium",
      "fontPostScriptName": "Inter-Medium",
      "fontWeight": 500,
      "fontSize": 28,
      "letterSpacing": 0,
      "lineHeight": 100,
      "isItalic": false
    },
    {
      "key": "h5",
      "fontFamily": "Inter Medium",
      "fontPostScriptName": "Inter-Medium",
      "fontWeight": 500,
      "fontSize": 24,
      "letterSpacing": 0,
      "lineHeight": 100,
      "isItalic": false
    },
    {
      "key": "h6",
      "fontFamily": "Inter Medium",
      "fontPostScriptName": "Inter-Medium",
      "fontWeight": 500,
      "fontSize": 20,
      "letterSpacing": 0,
      "lineHeight": 100,
      "isItalic": false
    },
    {
      "key": "body",
      "fontFamily": "Inter Regular",
      "fontPostScriptName": "Inter-Regular",
      "fontWeight": 400,
      "fontSize": 16,
      "letterSpacing": 0,
      "lineHeight": 100,
      "isItalic": false
    },
    {
      "key": "caption",
      "fontFamily": "Inter Regular",
      "fontPostScriptName": "Inter-Regular",
      "fontWeight": 400,
      "fontSize": 13,
      "letterSpacing": 0,
      "lineHeight": 100,
      "isItalic": false
    },
    {
      "key": "serif",
      "fontFamily": "Libre Baskerville Regular",
      "fontPostScriptName": "LibreBaskerville-Regular",
      "fontWeight": 400,
      "fontSize": 16,
      "letterSpacing": 0,
      "lineHeight": 100,
      "isItalic": false
    },
    {
      "key": "italic",
      "fontFamily": "Inter Italic",
      "fontPostScriptName": "Inter-Italic",
      "fontWeight": 400,
      "fontSize": 16,
      "letterSpacing": 0,
      "lineHeight": 100,
      "isItalic": true
    },
    {
      "key": "italic-serif",
      "fontFamily": "Libre Baskerville Italic",
      "fontPostScriptName": "LibreBaskerville-Italic",
      "fontWeight": 400,
      "fontSize": 16,
      "letterSpacing": 0,
      "lineHeight": 100,
      "isItalic": true
    },
    {
      "key": "strong",
      "fontFamily": "Inter SemiBold",
      "fontPostScriptName": "Inter-SemiBold",
      "fontWeight": 600,
      "fontSize": 16,
      "letterSpacing": 0,
      "lineHeight": 100,
      "isItalic": false
    },
    {
      "key": "strong-italic",
      "fontFamily": "Inter SemiBold Italic",
      "fontPostScriptName": "Inter-SemiBoldItalic",
      "fontWeight": 600,
      "fontSize": 16,
      "letterSpacing": 0,
      "lineHeight": 100,
      "isItalic": true
    },
    {
      "key": "strong-serif",
      "fontFamily": "Libre Baskerville Bold",
      "fontPostScriptName": "LibreBaskerville-Bold",
      "fontWeight": 700,
      "fontSize": 16,
      "letterSpacing": 0,
      "lineHeight": 100,
      "isItalic": false
    }
  ],
  "iconography": [
    {
      "key": "arithmetic",
      "url": "https://figma-alpha-api.s3.us-west-2.amazonaws.com/images/92525dfb-cb9f-4cf5-afa6-8f03a04fddd8"
    },
    {
      "key": "arrow-down",
      "url": "https://figma-alpha-api.s3.us-west-2.amazonaws.com/images/ca56fc73-4d01-4988-be3f-e9ed37f976ef"
    },
    {
      "key": "arrow-input",
      "url": "https://figma-alpha-api.s3.us-west-2.amazonaws.com/images/e8368a6d-e66b-4fd4-9959-0cffe58ab984"
    },
    {
      "key": "arrow-left",
      "url": "https://figma-alpha-api.s3.us-west-2.amazonaws.com/images/c58ac4ee-f8bb-4f87-99d0-af1e08c3cb8d"
    },
    {
      "key": "arrow-output",
      "url": "https://figma-alpha-api.s3.us-west-2.amazonaws.com/images/eea1ddd8-0008-411a-92a7-da4268f12460"
    },
    {
      "key": "arrow-reset",
      "url": "https://figma-alpha-api.s3.us-west-2.amazonaws.com/images/59189876-ff98-4bad-813c-8673017fe74e"
    },
    {
      "key": "arrow-right",
      "url": "https://figma-alpha-api.s3.us-west-2.amazonaws.com/images/61e7a72f-3831-44ab-8a04-def98abff5a5"
    },
    {
      "key": "arrow-shuffle",
      "url": "https://figma-alpha-api.s3.us-west-2.amazonaws.com/images/3acb232b-922d-4b5b-9b9a-9f3c74748af4"
    },
    {
      "key": "arrow-up",
      "url": "https://figma-alpha-api.s3.us-west-2.amazonaws.com/images/2ba47333-8c49-47fb-ae1b-337b3d95c76d"
    },
    {
      "key": "bar-chart",
      "url": "https://figma-alpha-api.s3.us-west-2.amazonaws.com/images/3723cb56-e8e0-445c-921e-0901d920af5e"
    },
    {
      "key": "checkmark",
      "url": "https://figma-alpha-api.s3.us-west-2.amazonaws.com/images/8c3c80e3-1ef3-4f42-ad9f-a4c593fef11c"
    },
    {
      "key": "checkmark-circle",
      "url": "https://figma-alpha-api.s3.us-west-2.amazonaws.com/images/afca0776-7ac6-48fb-a7c8-c9b46b313b0f"
    },
    {
      "key": "checkmark-circle-filled",
      "url": "https://figma-alpha-api.s3.us-west-2.amazonaws.com/images/6a7da0d2-0fe7-47ab-89f8-0b106ff33cc9"
    },
    {
      "key": "chevron-down",
      "url": "https://figma-alpha-api.s3.us-west-2.amazonaws.com/images/fae7a09e-1d5b-4c9f-9e5b-cebbc5a43751"
    },
    {
      "key": "chevron-left",
      "url": "https://figma-alpha-api.s3.us-west-2.amazonaws.com/images/9eaef498-3deb-4b42-b378-1fc5038c3cbb"
    },
    {
      "key": "chevron-right",
      "url": "https://figma-alpha-api.s3.us-west-2.amazonaws.com/images/b41dd443-53c8-4f1f-92c8-1970b55c970e"
    },
    {
      "key": "chevron-up",
      "url": "https://figma-alpha-api.s3.us-west-2.amazonaws.com/images/12282b66-c00d-479a-8640-efb88f8141f4"
    },
    {
      "key": "clear",
      "url": "https://figma-alpha-api.s3.us-west-2.amazonaws.com/images/1515946c-f3e5-454d-ba84-1ab30cef975d"
    },
    {
      "key": "clock",
      "url": "https://figma-alpha-api.s3.us-west-2.amazonaws.com/images/3d8432ba-5810-4f89-a825-b8691255dcb7"
    },
    {
      "key": "crown",
      "url": "https://figma-alpha-api.s3.us-west-2.amazonaws.com/images/3339f7f7-fef2-4a51-af34-623006a7be41"
    },
    {
      "key": "cup",
      "url": "https://figma-alpha-api.s3.us-west-2.amazonaws.com/images/04985d90-391c-4c76-9242-0894fe7c38cb"
    },
    {
      "key": "delete",
      "url": "https://figma-alpha-api.s3.us-west-2.amazonaws.com/images/1978d2bb-8954-41fd-bfc5-d412c0473814"
    },
    {
      "key": "dictionary",
      "url": "https://figma-alpha-api.s3.us-west-2.amazonaws.com/images/62d3bf27-7d5e-4085-ac99-08ca71353854"
    },
    {
      "key": "dictionary-english",
      "url": "https://figma-alpha-api.s3.us-west-2.amazonaws.com/images/c687f9a4-89d7-4104-aaf1-1530500cb9c2"
    },
    {
      "key": "dictionary-finnish",
      "url": "https://figma-alpha-api.s3.us-west-2.amazonaws.com/images/70e13342-ee09-4866-9c82-f9039b06f032"
    },
    {
      "key": "dictionary-spanish",
      "url": "https://figma-alpha-api.s3.us-west-2.amazonaws.com/images/94321b39-a691-4206-8be5-9952793479b6"
    },
    {
      "key": "dictionary-swedish",
      "url": "https://figma-alpha-api.s3.us-west-2.amazonaws.com/images/71ca2484-4f7b-489c-bfcc-689c84b4e8c3"
    },
    {
      "key": "die-five",
      "url": "https://figma-alpha-api.s3.us-west-2.amazonaws.com/images/d6cbaa6e-49a4-48d4-810b-1761191816d0"
    },
    {
      "key": "die-four",
      "url": "https://figma-alpha-api.s3.us-west-2.amazonaws.com/images/a98e31c8-a6cc-487c-8496-4bda19c95d7d"
    },
    {
      "key": "die-one",
      "url": "https://figma-alpha-api.s3.us-west-2.amazonaws.com/images/09ff5329-b142-418f-89b0-3c9b5419e43c"
    },
    {
      "key": "die-six",
      "url": "https://figma-alpha-api.s3.us-west-2.amazonaws.com/images/cdd06be0-886c-4a0a-94a7-5ebe15509b34"
    },
    {
      "key": "die-three",
      "url": "https://figma-alpha-api.s3.us-west-2.amazonaws.com/images/b3ae2648-a84a-45b0-b2f1-44cec295f576"
    },
    {
      "key": "die-two",
      "url": "https://figma-alpha-api.s3.us-west-2.amazonaws.com/images/34e064f1-1861-4e3e-ae7f-ae36cc3e1b0f"
    },
    {
      "key": "divide",
      "url": "https://figma-alpha-api.s3.us-west-2.amazonaws.com/images/9a3ab20f-e911-4e95-8c22-e3425dec26ec"
    },
    {
      "key": "doc",
      "url": "https://figma-alpha-api.s3.us-west-2.amazonaws.com/images/b12c1957-de21-4b53-b7aa-ce86ce1e7d22"
    },
    {
      "key": "drop",
      "url": "https://figma-alpha-api.s3.us-west-2.amazonaws.com/images/a66a359f-a4b0-466b-a167-0a907cc87591"
    },
    {
      "key": "ear-waves",
      "url": "https://figma-alpha-api.s3.us-west-2.amazonaws.com/images/f4d6ae16-f775-45ca-b49f-efe87987a51b"
    },
    {
      "key": "filter",
      "url": "https://figma-alpha-api.s3.us-west-2.amazonaws.com/images/fd50924c-d8bf-4a19-98af-f8820f6ce64f"
    },
    {
      "key": "flag",
      "url": "https://figma-alpha-api.s3.us-west-2.amazonaws.com/images/958b83be-e470-4b28-a37a-b568f25c7d28"
    },
    {
      "key": "flame",
      "url": "https://figma-alpha-api.s3.us-west-2.amazonaws.com/images/c1ea283c-4929-472e-967e-8b4a6abf4399"
    },
    {
      "key": "footprint",
      "url": "https://figma-alpha-api.s3.us-west-2.amazonaws.com/images/eb7f7f28-cf7a-4b28-a797-73c4951154a5"
    },
    {
      "key": "gamepad",
      "url": "https://figma-alpha-api.s3.us-west-2.amazonaws.com/images/5ac99177-bffc-4917-9f52-567327454886"
    },
    {
      "key": "gear",
      "url": "https://figma-alpha-api.s3.us-west-2.amazonaws.com/images/7261300a-1a21-41a8-b090-141280e418b5"
    },
    {
      "key": "globe",
      "url": "https://figma-alpha-api.s3.us-west-2.amazonaws.com/images/ac045739-c3e4-4165-b63f-71ede2c1c98f"
    },
    {
      "key": "heart",
      "url": "https://figma-alpha-api.s3.us-west-2.amazonaws.com/images/74675977-34ea-42f7-a2b3-9388ce32d565"
    },
    {
      "key": "heart-filled",
      "url": "https://figma-alpha-api.s3.us-west-2.amazonaws.com/images/bd870820-e7db-49c4-9cf1-b3d2ee79ddce"
    },
    {
      "key": "hint",
      "url": "https://figma-alpha-api.s3.us-west-2.amazonaws.com/images/7c3d85a8-2b8e-4706-9003-402cbdbb02ac"
    },
    {
      "key": "history",
      "url": "https://figma-alpha-api.s3.us-west-2.amazonaws.com/images/6510899b-3b6f-4c23-8efb-32dc2462a30b"
    },
    {
      "key": "image",
      "url": "https://figma-alpha-api.s3.us-west-2.amazonaws.com/images/a21b23be-6b4e-484d-bb4e-b3bcbd3ca3c1"
    },
    {
      "key": "info-circle",
      "url": "https://figma-alpha-api.s3.us-west-2.amazonaws.com/images/2ad0e89b-ba65-4bc8-bf1c-bba37b7c54cf"
    },
    {
      "key": "language-english",
      "url": "https://figma-alpha-api.s3.us-west-2.amazonaws.com/images/37620d1a-d221-4359-bb80-5f4fde01f307"
    },
    {
      "key": "language-finnish",
      "url": "https://figma-alpha-api.s3.us-west-2.amazonaws.com/images/af6e5eda-691b-4d8e-8d37-fb80519e8d3c"
    },
    {
      "key": "language-spanish",
      "url": "https://figma-alpha-api.s3.us-west-2.amazonaws.com/images/cdac5d13-4898-4d05-90c8-006f92df3e14"
    },
    {
      "key": "language-swedish",
      "url": "https://figma-alpha-api.s3.us-west-2.amazonaws.com/images/36a98baf-5b4a-4ca4-a0e4-1df3a86eb55f"
    },
    {
      "key": "leaf",
      "url": "https://figma-alpha-api.s3.us-west-2.amazonaws.com/images/2d06c0f9-4a45-4b79-b275-ea10ce195180"
    },
    {
      "key": "lighning",
      "url": "https://figma-alpha-api.s3.us-west-2.amazonaws.com/images/87dd10e9-b25b-425b-ba75-f9be1fa0325e"
    },
    {
      "key": "lightbulb",
      "url": "https://figma-alpha-api.s3.us-west-2.amazonaws.com/images/62837821-8bb6-4636-a0ea-65fae2e928fe"
    },
    {
      "key": "link",
      "url": "https://figma-alpha-api.s3.us-west-2.amazonaws.com/images/9ca95360-b27c-44f1-98af-db3c6ec84c9e"
    },
    {
      "key": "magnifying-glass",
      "url": "https://figma-alpha-api.s3.us-west-2.amazonaws.com/images/b10c7442-7884-48ea-a664-a47699e96a01"
    },
    {
      "key": "medal",
      "url": "https://figma-alpha-api.s3.us-west-2.amazonaws.com/images/546fc21a-64d4-4ffc-8cc6-007d80ea0ecb"
    },
    {
      "key": "minus",
      "url": "https://figma-alpha-api.s3.us-west-2.amazonaws.com/images/b6429ade-6f7e-4493-b8f7-176109727acf"
    },
    {
      "key": "minus-circle",
      "url": "https://figma-alpha-api.s3.us-west-2.amazonaws.com/images/a4251283-b4fa-420a-86fc-a60125d7f661"
    },
    {
      "key": "multiply",
      "url": "https://figma-alpha-api.s3.us-west-2.amazonaws.com/images/f4ccbf67-7b33-4e19-b5e4-5c66f70d1340"
    },
    {
      "key": "paperplane",
      "url": "https://figma-alpha-api.s3.us-west-2.amazonaws.com/images/8c2d19ca-170a-4959-a8f5-887c037fed95"
    },
    {
      "key": "pause",
      "url": "https://figma-alpha-api.s3.us-west-2.amazonaws.com/images/e38cdef7-21bd-429b-bd8a-25dc840381c2"
    },
    {
      "key": "pen",
      "url": "https://figma-alpha-api.s3.us-west-2.amazonaws.com/images/1502db5b-87bb-4fe6-8c9f-92039240eb98"
    },
    {
      "key": "percent",
      "url": "https://figma-alpha-api.s3.us-west-2.amazonaws.com/images/83a25521-548e-456e-bfb2-ce691aa3ad11"
    },
    {
      "key": "pie-chart",
      "url": "https://figma-alpha-api.s3.us-west-2.amazonaws.com/images/0ae56fd6-bf12-4b75-969e-c7563e06fcc1"
    },
    {
      "key": "pitcher",
      "url": "https://figma-alpha-api.s3.us-west-2.amazonaws.com/images/9fd469f9-15a3-40a1-bc39-4a51f3cb3bb4"
    },
    {
      "key": "play",
      "url": "https://figma-alpha-api.s3.us-west-2.amazonaws.com/images/839995d9-1ead-49bb-8db6-4aeaf39dba0c"
    },
    {
      "key": "plus",
      "url": "https://figma-alpha-api.s3.us-west-2.amazonaws.com/images/01984a1e-dbbb-4739-84be-4a2bef29304a"
    },
    {
      "key": "plus-circle",
      "url": "https://figma-alpha-api.s3.us-west-2.amazonaws.com/images/c7861c31-40e1-475f-b507-f1cd9a08e4ba"
    },
    {
      "key": "question-mark-circle",
      "url": "https://figma-alpha-api.s3.us-west-2.amazonaws.com/images/fe6301d4-bfaa-456e-8784-c10b383f3bad"
    },
    {
      "key": "radio-circle",
      "url": "https://figma-alpha-api.s3.us-west-2.amazonaws.com/images/9552b05a-c492-4fe7-aa11-0f833a73b650"
    },
    {
      "key": "radio-circle-filled",
      "url": "https://figma-alpha-api.s3.us-west-2.amazonaws.com/images/20791482-d99b-4d68-9e3b-edf8ce76c27d"
    },
    {
      "key": "ruler",
      "url": "https://figma-alpha-api.s3.us-west-2.amazonaws.com/images/cd9e5760-60ff-4692-b00a-2d8a15264917"
    },
    {
      "key": "scale",
      "url": "https://figma-alpha-api.s3.us-west-2.amazonaws.com/images/30565ebe-2856-400d-adc8-bb55dbaa9d89"
    },
    {
      "key": "shared",
      "url": "https://figma-alpha-api.s3.us-west-2.amazonaws.com/images/34ed0a81-7971-4e28-b10b-389ab7967bbe"
    },
    {
      "key": "skip",
      "url": "https://figma-alpha-api.s3.us-west-2.amazonaws.com/images/4d91ad40-144f-41e7-bd9e-8ef6ce1d8806"
    },
    {
      "key": "spinner",
      "url": "https://figma-alpha-api.s3.us-west-2.amazonaws.com/images/1a02f82f-cb04-4200-adb9-576c123d9870"
    },
    {
      "key": "star",
      "url": "https://figma-alpha-api.s3.us-west-2.amazonaws.com/images/baa7ff74-2bc3-471d-a4d6-831a26c1fde7"
    },
    {
      "key": "star-filled",
      "url": "https://figma-alpha-api.s3.us-west-2.amazonaws.com/images/4c495dd6-8367-4853-adc9-d878fdbcf104"
    },
    {
      "key": "stop",
      "url": "https://figma-alpha-api.s3.us-west-2.amazonaws.com/images/05d609cd-3041-47e5-981a-aaed1eea2397"
    },
    {
      "key": "table-spoon",
      "url": "https://figma-alpha-api.s3.us-west-2.amazonaws.com/images/fce93dcd-b6c6-49dc-af3d-dcc172a8e000"
    },
    {
      "key": "tag",
      "url": "https://figma-alpha-api.s3.us-west-2.amazonaws.com/images/a2880acc-1bd8-4a9e-9789-1927fcbd98b3"
    },
    {
      "key": "tea-spoon",
      "url": "https://figma-alpha-api.s3.us-west-2.amazonaws.com/images/eb899311-da58-4912-a9e1-e7637e1e7425"
    },
    {
      "key": "team",
      "url": "https://figma-alpha-api.s3.us-west-2.amazonaws.com/images/92bf7df9-352f-4dc5-98a4-76a980e46b93"
    },
    {
      "key": "thermometer-high",
      "url": "https://figma-alpha-api.s3.us-west-2.amazonaws.com/images/047f5deb-5309-4afa-861a-da76a60a2476"
    },
    {
      "key": "thermometer-low",
      "url": "https://figma-alpha-api.s3.us-west-2.amazonaws.com/images/d1fdb4fe-169c-42a4-ac6e-59dac48e82a0"
    },
    {
      "key": "thermometer-medium",
      "url": "https://figma-alpha-api.s3.us-west-2.amazonaws.com/images/9b963239-1a53-4bfb-b32d-4c6c8cafd814"
    },
    {
      "key": "translation",
      "url": "https://figma-alpha-api.s3.us-west-2.amazonaws.com/images/3ab65b4d-cbfd-46aa-bb35-ac3ed62bbeb0"
    },
    {
      "key": "trash",
      "url": "https://figma-alpha-api.s3.us-west-2.amazonaws.com/images/284a0730-b4d9-4ac2-9589-3a56e09ab19e"
    },
    {
      "key": "wand",
      "url": "https://figma-alpha-api.s3.us-west-2.amazonaws.com/images/fb1b2161-fe8c-4bd6-b804-8aba62976859"
    },
    {
      "key": "web-search",
      "url": "https://figma-alpha-api.s3.us-west-2.amazonaws.com/images/c7732b1b-a6a6-4b4c-8cd3-29c169f63c51"
    },
    {
      "key": "weight",
      "url": "https://figma-alpha-api.s3.us-west-2.amazonaws.com/images/2a93a4fa-2a24-4cf9-ab53-7fd3c1ba45ae"
    },
    {
      "key": "wikipedia",
      "url": "https://figma-alpha-api.s3.us-west-2.amazonaws.com/images/8a2c633c-992c-4acd-aac6-05a216d0eff7"
    },
    {
      "key": "xmark",
      "url": "https://figma-alpha-api.s3.us-west-2.amazonaws.com/images/09bb00e5-1515-4fcc-b372-c047475f67dd"
    },
    {
      "key": "xmark-circle",
      "url": "https://figma-alpha-api.s3.us-west-2.amazonaws.com/images/5d6bc608-f031-4bb1-96d6-88c5021a0d6f"
    },
    {
      "key": "xmark-circle-filled",
      "url": "https://figma-alpha-api.s3.us-west-2.amazonaws.com/images/4a3bf5b8-c8a3-4b56-9623-7dd88f592235"
    }
  ]
}