{
  "palette": [
    {
      "scheme": "dark",
      "name": "yinyang",
      "hexCode": "E0E4EB",
      "r": 0.8799999952316284,
      "g": 0.8933334350585938,
      "b": 0.9200000166893005,
      "a": 1
    },
    {
      "scheme": "light",
      "name": "yinyang",
      "hexCode": "29303D",
      "r": 0.1600000113248825,
      "g": 0.18666668236255646,
      "b": 0.23999999463558197,
      "a": 1
    },
    {
      "scheme": "dark",
      "name": "indigo",
      "hexCode": "667FFF",
      "r": 0.4000000059604645,
      "g": 0.4999999403953552,
      "b": 1,
      "a": 1
    },
    {
      "scheme": "light",
      "name": "indigo",
      "hexCode": "3D5CF5",
      "r": 0.23999999463558197,
      "g": 0.35999995470046997,
      "b": 0.9599999785423279,
      "a": 1
    },
    {
      "scheme": "dark",
      "name": "blue",
      "hexCode": "42C4F0",
      "r": 0.2600000500679016,
      "g": 0.7699999809265137,
      "b": 0.9399999976158142,
      "a": 1
    },
    {
      "scheme": "light",
      "name": "blue",
      "hexCode": "0B96DA",
      "r": 0.044999998062849045,
      "g": 0.5874770879745483,
      "b": 0.8549999594688416,
      "a": 1
    },
    {
      "scheme": "dark",
      "name": "mint",
      "hexCode": "06E0BB",
      "r": 0.022499997168779373,
      "g": 0.8774998784065247,
      "b": 0.7350000143051147,
      "a": 1
    },
    {
      "scheme": "light",
      "name": "mint",
      "hexCode": "00B295",
      "r": 0,
      "g": 0.699999988079071,
      "b": 0.5833333134651184,
      "a": 1
    },
    {
      "scheme": "dark",
      "name": "green",
      "hexCode": "66CC52",
      "r": 0.40000003576278687,
      "g": 0.800000011920929,
      "b": 0.3199999928474426,
      "a": 1
    },
    {
      "scheme": "light",
      "name": "green",
      "hexCode": "4AB236",
      "r": 0.291666716337204,
      "g": 0.699999988079071,
      "b": 0.21000000834465027,
      "a": 1
    },
    {
      "scheme": "dark",
      "name": "yellow",
      "hexCode": "E8BA30",
      "r": 0.9100000262260437,
      "g": 0.7299999594688416,
      "b": 0.1900000125169754,
      "a": 1
    },
    {
      "scheme": "light",
      "name": "yellow",
      "hexCode": "CC9900",
      "r": 0.800000011920929,
      "g": 0.6000000238418579,
      "b": 0,
      "a": 1
    },
    {
      "scheme": "dark",
      "name": "orange",
      "hexCode": "FF8833",
      "r": 1,
      "g": 0.5333331823348999,
      "b": 0.20000000298023224,
      "a": 1
    },
    {
      "scheme": "light",
      "name": "orange",
      "hexCode": "F26C0C",
      "r": 0.949999988079071,
      "g": 0.42354151606559753,
      "b": 0.047500014305114746,
      "a": 1
    },
    {
      "scheme": "dark",
      "name": "brown",
      "hexCode": "D99A6C",
      "r": 0.8500000238418579,
      "g": 0.6020832061767578,
      "b": 0.42500001192092896,
      "a": 1
    },
    {
      "scheme": "light",
      "name": "brown",
      "hexCode": "A66C42",
      "r": 0.6499999761581421,
      "g": 0.42249995470046997,
      "b": 0.25999999046325684,
      "a": 1
    },
    {
      "scheme": "dark",
      "name": "red",
      "hexCode": "FF4D5B",
      "r": 1,
      "g": 0.30000004172325134,
      "b": 0.35833337903022766,
      "a": 1
    },
    {
      "scheme": "light",
      "name": "red",
      "hexCode": "E53948",
      "r": 0.8999999761581421,
      "g": 0.2250000238418579,
      "b": 0.2812500298023224,
      "a": 1
    },
    {
      "scheme": "dark",
      "name": "pink",
      "hexCode": "F261C2",
      "r": 0.949999988079071,
      "g": 0.3799999952316284,
      "b": 0.7599998712539673,
      "a": 1
    },
    {
      "scheme": "light",
      "name": "pink",
      "hexCode": "E550B4",
      "r": 0.8999999761581421,
      "g": 0.3149999976158142,
      "b": 0.7049999237060547,
      "a": 1
    },
    {
      "scheme": "dark",
      "name": "purple",
      "hexCode": "AD73FF",
      "r": 0.6791666746139526,
      "g": 0.44999998807907104,
      "b": 1,
      "a": 1
    },
    {
      "scheme": "light",
      "name": "purple",
      "hexCode": "7E47EB",
      "r": 0.4933331608772278,
      "g": 0.2800000309944153,
      "b": 0.9200000166893005,
      "a": 1
    },
    {
      "scheme": "dark",
      "name": "accessory",
      "hexCode": "5C6B8A",
      "r": 0.35999998450279236,
      "g": 0.41999998688697815,
      "b": 0.5400000214576721,
      "a": 1
    },
    {
      "scheme": "light",
      "name": "accessory",
      "hexCode": "C2C9D6",
      "r": 0.7599999904632568,
      "g": 0.7866666913032532,
      "b": 0.8399999737739563,
      "a": 1
    },
    {
      "scheme": "dark",
      "name": "tertiary body",
      "hexCode": "7585A3",
      "r": 0.4599999785423279,
      "g": 0.5199999809265137,
      "b": 0.6399999856948853,
      "a": 1
    },
    {
      "scheme": "light",
      "name": "tertiary body",
      "hexCode": "A3ADC2",
      "r": 0.6399999856948853,
      "g": 0.6800000071525574,
      "b": 0.7600000500679016,
      "a": 1
    },
    {
      "scheme": "dark",
      "name": "secondary body",
      "hexCode": "A3ADC2",
      "r": 0.6399999856948853,
      "g": 0.6800000071525574,
      "b": 0.7600000500679016,
      "a": 1
    },
    {
      "scheme": "light",
      "name": "secondary body",
      "hexCode": "667799",
      "r": 0.4000000059604645,
      "g": 0.46666666865348816,
      "b": 0.6000000238418579,
      "a": 1
    },
    {
      "scheme": "dark",
      "name": "body",
      "hexCode": "F0F1F5",
      "r": 0.9399999976158142,
      "g": 0.9466666579246521,
      "b": 0.9600000381469727,
      "a": 1
    },
    {
      "scheme": "light",
      "name": "body",
      "hexCode": "29303D",
      "r": 0.1600000113248825,
      "g": 0.18666668236255646,
      "b": 0.23999999463558197,
      "a": 1
    },
    {
      "scheme": "dark",
      "name": "tertiary background",
      "hexCode": "000000",
      "r": 0,
      "g": 0,
      "b": 0,
      "a": 1
    },
    {
      "scheme": "light",
      "name": "tertiary background",
      "hexCode": "E0E4EB",
      "r": 0.8799999952316284,
      "g": 0.8933334350585938,
      "b": 0.9200000166893005,
      "a": 1
    },
    {
      "scheme": "dark",
      "name": "secondary background",
      "hexCode": "0A0C0F",
      "r": 0.03999999910593033,
      "g": 0.046666666865348816,
      "b": 0.06000000238418579,
      "a": 1
    },
    {
      "scheme": "light",
      "name": "secondary background",
      "hexCode": "F0F1F5",
      "r": 0.9399999976158142,
      "g": 0.9466666579246521,
      "b": 0.9600000381469727,
      "a": 1
    },
    {
      "scheme": "dark",
      "name": "background",
      "hexCode": "1F242E",
      "r": 0.12000000476837158,
      "g": 0.14000001549720764,
      "b": 0.17999999225139618,
      "a": 1
    },
    {
      "scheme": "light",
      "name": "background",
      "hexCode": "FFFFFF",
      "r": 1,
      "g": 1,
      "b": 1,
      "a": 1
    }
  ],
  "typography": [
    {
      "key": "h1",
      "fontFamily": "Inter Medium",
      "fontPostScriptName": "Inter-Medium",
      "fontWeight": 500,
      "fontSize": 48,
      "letterSpacing": 0,
      "lineHeight": 100,
      "isItalic": false
    },
    {
      "key": "h1 italic",
      "fontFamily": "Inter Medium Italic",
      "fontPostScriptName": "Inter-MediumItalic",
      "fontWeight": 500,
      "fontSize": 48,
      "letterSpacing": 0,
      "lineHeight": 100,
      "isItalic": true
    },
    {
      "key": "h1 serif",
      "fontFamily": "Libre Baskerville Regular",
      "fontPostScriptName": "LibreBaskerville-Regular",
      "fontWeight": 400,
      "fontSize": 48,
      "letterSpacing": 0,
      "lineHeight": 100,
      "isItalic": false
    },
    {
      "key": "h2",
      "fontFamily": "Inter Medium",
      "fontPostScriptName": "Inter-Medium",
      "fontWeight": 500,
      "fontSize": 40,
      "letterSpacing": 0,
      "lineHeight": 100,
      "isItalic": false
    },
    {
      "key": "h2 italic",
      "fontFamily": "Inter Medium Italic",
      "fontPostScriptName": "Inter-MediumItalic",
      "fontWeight": 500,
      "fontSize": 40,
      "letterSpacing": 0,
      "lineHeight": 100,
      "isItalic": true
    },
    {
      "key": "h2 serif",
      "fontFamily": "Libre Baskerville Regular",
      "fontPostScriptName": "LibreBaskerville-Regular",
      "fontWeight": 400,
      "fontSize": 40,
      "letterSpacing": 0,
      "lineHeight": 100,
      "isItalic": false
    },
    {
      "key": "h3",
      "fontFamily": "Inter Medium",
      "fontPostScriptName": "Inter-Medium",
      "fontWeight": 500,
      "fontSize": 32,
      "letterSpacing": 0,
      "lineHeight": 100,
      "isItalic": false
    },
    {
      "key": "h3 italic",
      "fontFamily": "Inter Medium Italic",
      "fontPostScriptName": "Inter-MediumItalic",
      "fontWeight": 500,
      "fontSize": 32,
      "letterSpacing": 0,
      "lineHeight": 100,
      "isItalic": true
    },
    {
      "key": "h3 serif",
      "fontFamily": "Libre Baskerville Regular",
      "fontPostScriptName": "LibreBaskerville-Regular",
      "fontWeight": 400,
      "fontSize": 32,
      "letterSpacing": 0,
      "lineHeight": 100,
      "isItalic": false
    },
    {
      "key": "h4",
      "fontFamily": "Inter Medium",
      "fontPostScriptName": "Inter-Medium",
      "fontWeight": 500,
      "fontSize": 28,
      "letterSpacing": 0,
      "lineHeight": 100,
      "isItalic": false
    },
    {
      "key": "h4 italic",
      "fontFamily": "Inter Medium Italic",
      "fontPostScriptName": "Inter-MediumItalic",
      "fontWeight": 500,
      "fontSize": 28,
      "letterSpacing": 0,
      "lineHeight": 100,
      "isItalic": true
    },
    {
      "key": "h4 serif",
      "fontFamily": "Libre Baskerville Regular",
      "fontPostScriptName": "LibreBaskerville-Regular",
      "fontWeight": 400,
      "fontSize": 28,
      "letterSpacing": 0,
      "lineHeight": 100,
      "isItalic": false
    },
    {
      "key": "h5",
      "fontFamily": "Inter Medium",
      "fontPostScriptName": "Inter-Medium",
      "fontWeight": 500,
      "fontSize": 24,
      "letterSpacing": 0,
      "lineHeight": 100,
      "isItalic": false
    },
    {
      "key": "h5 italic",
      "fontFamily": "Inter Medium Italic",
      "fontPostScriptName": "Inter-MediumItalic",
      "fontWeight": 500,
      "fontSize": 24,
      "letterSpacing": 0,
      "lineHeight": 100,
      "isItalic": true
    },
    {
      "key": "h5 serif",
      "fontFamily": "Libre Baskerville Regular",
      "fontPostScriptName": "LibreBaskerville-Regular",
      "fontWeight": 400,
      "fontSize": 24,
      "letterSpacing": 0,
      "lineHeight": 100,
      "isItalic": false
    },
    {
      "key": "h6",
      "fontFamily": "Inter Medium",
      "fontPostScriptName": "Inter-Medium",
      "fontWeight": 500,
      "fontSize": 20,
      "letterSpacing": 0,
      "lineHeight": 100,
      "isItalic": false
    },
    {
      "key": "h6 italic",
      "fontFamily": "Inter Medium Italic",
      "fontPostScriptName": "Inter-MediumItalic",
      "fontWeight": 500,
      "fontSize": 20,
      "letterSpacing": 0,
      "lineHeight": 100,
      "isItalic": true
    },
    {
      "key": "h6 serif",
      "fontFamily": "Libre Baskerville Regular",
      "fontPostScriptName": "LibreBaskerville-Regular",
      "fontWeight": 400,
      "fontSize": 20,
      "letterSpacing": 0,
      "lineHeight": 100,
      "isItalic": false
    },
    {
      "key": "body",
      "fontFamily": "Inter Regular",
      "fontPostScriptName": "Inter-Regular",
      "fontWeight": 400,
      "fontSize": 16,
      "letterSpacing": 0,
      "lineHeight": 100,
      "isItalic": false
    },
    {
      "key": "serif",
      "fontFamily": "Libre Baskerville Regular",
      "fontPostScriptName": "LibreBaskerville-Regular",
      "fontWeight": 400,
      "fontSize": 16,
      "letterSpacing": 0,
      "lineHeight": 100,
      "isItalic": false
    },
    {
      "key": "italic",
      "fontFamily": "Inter Italic",
      "fontPostScriptName": "Inter-Italic",
      "fontWeight": 400,
      "fontSize": 16,
      "letterSpacing": 0,
      "lineHeight": 100,
      "isItalic": true
    },
    {
      "key": "italic serif",
      "fontFamily": "Libre Baskerville Italic",
      "fontPostScriptName": "LibreBaskerville-Italic",
      "fontWeight": 400,
      "fontSize": 16,
      "letterSpacing": 0,
      "lineHeight": 100,
      "isItalic": true
    },
    {
      "key": "strong",
      "fontFamily": "Inter SemiBold",
      "fontPostScriptName": "Inter-SemiBold",
      "fontWeight": 600,
      "fontSize": 16,
      "letterSpacing": 0,
      "lineHeight": 100,
      "isItalic": false
    },
    {
      "key": "strong italic",
      "fontFamily": "Inter SemiBold Italic",
      "fontPostScriptName": "Inter-SemiBoldItalic",
      "fontWeight": 600,
      "fontSize": 16,
      "letterSpacing": 0,
      "lineHeight": 100,
      "isItalic": true
    },
    {
      "key": "strong serif",
      "fontFamily": "Libre Baskerville Bold",
      "fontPostScriptName": "LibreBaskerville-Bold",
      "fontWeight": 700,
      "fontSize": 16,
      "letterSpacing": 0,
      "lineHeight": 100,
      "isItalic": false
    },
    {
      "key": "footnote",
      "fontFamily": "Inter Regular",
      "fontPostScriptName": "Inter-Regular",
      "fontWeight": 400,
      "fontSize": 13,
      "letterSpacing": 0,
      "lineHeight": 100,
      "isItalic": false
    },
    {
      "key": "caption",
      "fontFamily": "Inter Medium",
      "fontPostScriptName": "Inter-Medium",
      "fontWeight": 500,
      "fontSize": 13,
      "letterSpacing": 0,
      "lineHeight": 100,
      "isItalic": false
    },
    {
      "key": "caption all-caps",
      "fontFamily": "Inter Medium",
      "fontPostScriptName": "Inter-Medium",
      "fontWeight": 500,
      "fontSize": 13,
      "letterSpacing": 1.3,
      "lineHeight": 100,
      "textCase": "UPPER",
      "isItalic": false
    }
  ],
  "iconography": [
    {
      "key": "add",
      "url": "https://figma-alpha-api.s3.us-west-2.amazonaws.com/images/f119e255-3fde-4988-b207-bf46bc1f65b8"
    },
    {
      "key": "arithmetic",
      "url": "https://figma-alpha-api.s3.us-west-2.amazonaws.com/images/54762680-b03c-47a3-b633-1a2ce0bb13b1"
    },
    {
      "key": "arrow-down",
      "url": "https://figma-alpha-api.s3.us-west-2.amazonaws.com/images/ca1f4c40-f04a-4879-bc9b-4357a2e33b66"
    },
    {
      "key": "arrow-left",
      "url": "https://figma-alpha-api.s3.us-west-2.amazonaws.com/images/322b10fd-5340-4e20-a31a-dae34ae8ac46"
    },
    {
      "key": "arrow-reset",
      "url": "https://figma-alpha-api.s3.us-west-2.amazonaws.com/images/c183a763-9ce7-41f9-8375-1661389c1c0b"
    },
    {
      "key": "arrow-right",
      "url": "https://figma-alpha-api.s3.us-west-2.amazonaws.com/images/07f45404-e69b-4cf3-9d6d-e5fe1eae2b22"
    },
    {
      "key": "arrow-shuffle",
      "url": "https://figma-alpha-api.s3.us-west-2.amazonaws.com/images/36669326-65e8-4474-9efd-35b4ad3775b1"
    },
    {
      "key": "arrow-up",
      "url": "https://figma-alpha-api.s3.us-west-2.amazonaws.com/images/ca9ad0f3-5318-499b-bb8e-e97c3fadde5e"
    },
    {
      "key": "basics",
      "url": "https://figma-alpha-api.s3.us-west-2.amazonaws.com/images/30e4b18b-8967-4fff-9f91-488cea93df3f"
    },
    {
      "key": "checkmark",
      "url": "https://figma-alpha-api.s3.us-west-2.amazonaws.com/images/35af9252-b272-42fc-bd85-1f7dbdbf3393"
    },
    {
      "key": "delete",
      "url": "https://figma-alpha-api.s3.us-west-2.amazonaws.com/images/bcb1cd5e-d9e6-482b-b913-b360d3c271a3"
    },
    {
      "key": "dictionary",
      "url": "https://figma-alpha-api.s3.us-west-2.amazonaws.com/images/e4b82c74-a55c-4bc4-bdf2-20cd25cb7efd"
    },
    {
      "key": "die-five",
      "url": "https://figma-alpha-api.s3.us-west-2.amazonaws.com/images/abaaf860-1eba-4bda-aac7-adda06858dc7"
    },
    {
      "key": "die-four",
      "url": "https://figma-alpha-api.s3.us-west-2.amazonaws.com/images/2065ec7c-1f86-4231-9c9f-ed1dd9bc4d51"
    },
    {
      "key": "die-one",
      "url": "https://figma-alpha-api.s3.us-west-2.amazonaws.com/images/6f3d1a97-f52f-458b-952a-80e9ad614128"
    },
    {
      "key": "die-six",
      "url": "https://figma-alpha-api.s3.us-west-2.amazonaws.com/images/f8f08474-33b3-4ffa-bc9f-1bc8adbbc7bf"
    },
    {
      "key": "die-three",
      "url": "https://figma-alpha-api.s3.us-west-2.amazonaws.com/images/afee7ad4-a653-4251-bae5-9e7c50afc745"
    },
    {
      "key": "die-two",
      "url": "https://figma-alpha-api.s3.us-west-2.amazonaws.com/images/fe63dba9-e80f-435c-92d9-a8b4117e1b75"
    },
    {
      "key": "divide",
      "url": "https://figma-alpha-api.s3.us-west-2.amazonaws.com/images/397d671b-b06e-408e-9486-c8a0b431f658"
    },
    {
      "key": "drop",
      "url": "https://figma-alpha-api.s3.us-west-2.amazonaws.com/images/c53350fa-02e3-41be-8faf-a3a926048689"
    },
    {
      "key": "filter",
      "url": "https://figma-alpha-api.s3.us-west-2.amazonaws.com/images/38af03c0-db4f-47b9-9cef-eea2f1769bfe"
    },
    {
      "key": "flame",
      "url": "https://figma-alpha-api.s3.us-west-2.amazonaws.com/images/aacda16b-bb52-4fa6-9c35-45a1e7fb700a"
    },
    {
      "key": "gamepad",
      "url": "https://figma-alpha-api.s3.us-west-2.amazonaws.com/images/fcbe1ffa-9164-4e9f-9bd4-820a1ff7aa56"
    },
    {
      "key": "gear",
      "url": "https://figma-alpha-api.s3.us-west-2.amazonaws.com/images/25f7c68d-d555-4931-8704-81a00f715811"
    },
    {
      "key": "globe",
      "url": "https://figma-alpha-api.s3.us-west-2.amazonaws.com/images/ba607d2b-6cb9-44e5-9916-037d3394f078"
    },
    {
      "key": "heart",
      "url": "https://figma-alpha-api.s3.us-west-2.amazonaws.com/images/8b966a43-2c2f-48e9-acb5-84ce6c6c7134"
    },
    {
      "key": "help",
      "url": "https://figma-alpha-api.s3.us-west-2.amazonaws.com/images/c4dcbccc-0c92-4781-bff1-60c550e1c5f3"
    },
    {
      "key": "hint",
      "url": "https://figma-alpha-api.s3.us-west-2.amazonaws.com/images/5cf6676a-0df4-438c-abaf-b528804af375"
    },
    {
      "key": "history",
      "url": "https://figma-alpha-api.s3.us-west-2.amazonaws.com/images/8481728b-4b50-42e5-b00b-411121852356"
    },
    {
      "key": "image",
      "url": "https://figma-alpha-api.s3.us-west-2.amazonaws.com/images/c7fa974f-8be7-4300-94c0-33b73135355c"
    },
    {
      "key": "info",
      "url": "https://figma-alpha-api.s3.us-west-2.amazonaws.com/images/0f2a15fc-e35c-4ece-9b85-880b1de97fee"
    },
    {
      "key": "leaf",
      "url": "https://figma-alpha-api.s3.us-west-2.amazonaws.com/images/06f74418-fbaa-4f32-a8e5-3934fbce218c"
    },
    {
      "key": "lighning",
      "url": "https://figma-alpha-api.s3.us-west-2.amazonaws.com/images/732ec876-7b98-44aa-ad95-3f0bab0b9ecd"
    },
    {
      "key": "lightbulb",
      "url": "https://figma-alpha-api.s3.us-west-2.amazonaws.com/images/85e5179e-d59d-4653-92e1-d53f3038510c"
    },
    {
      "key": "link",
      "url": "https://figma-alpha-api.s3.us-west-2.amazonaws.com/images/477ccfa4-debe-4afb-b89d-970d6ca5e8f2"
    },
    {
      "key": "magnifying-glass",
      "url": "https://figma-alpha-api.s3.us-west-2.amazonaws.com/images/13a3a81b-6e9a-47b5-ab9b-b16994633329"
    },
    {
      "key": "minus",
      "url": "https://figma-alpha-api.s3.us-west-2.amazonaws.com/images/87a723ce-c4ec-41fa-9f5f-297c954a3c03"
    },
    {
      "key": "multiply",
      "url": "https://figma-alpha-api.s3.us-west-2.amazonaws.com/images/b8712221-2688-444a-9d4f-c37e584ad20c"
    },
    {
      "key": "pause",
      "url": "https://figma-alpha-api.s3.us-west-2.amazonaws.com/images/060cf7e5-5ad5-451c-8b3e-edda58c8c1f8"
    },
    {
      "key": "pen",
      "url": "https://figma-alpha-api.s3.us-west-2.amazonaws.com/images/0800eb69-faeb-453c-ba29-d7179b763525"
    },
    {
      "key": "percent",
      "url": "https://figma-alpha-api.s3.us-west-2.amazonaws.com/images/21e3d701-8a5e-4d12-9573-bbbc5820dbcf"
    },
    {
      "key": "play",
      "url": "https://figma-alpha-api.s3.us-west-2.amazonaws.com/images/f93a7695-3269-4eb6-8060-bacf069314dc"
    },
    {
      "key": "plus",
      "url": "https://figma-alpha-api.s3.us-west-2.amazonaws.com/images/3bafbc13-4d0d-4798-9b53-6f8aad7d6e04"
    },
    {
      "key": "puzzled",
      "url": "https://figma-alpha-api.s3.us-west-2.amazonaws.com/images/33ab78d6-31f8-4f78-a43c-34356a1a4072"
    },
    {
      "key": "question-mark",
      "url": "https://figma-alpha-api.s3.us-west-2.amazonaws.com/images/68d4914c-a83f-4846-82bb-f2d3e9c443f0"
    },
    {
      "key": "remove",
      "url": "https://figma-alpha-api.s3.us-west-2.amazonaws.com/images/1ee35ee5-854b-4bbc-93bb-5bb03d5685b3"
    },
    {
      "key": "right",
      "url": "https://figma-alpha-api.s3.us-west-2.amazonaws.com/images/fc84bb82-06bd-49bf-bb76-d49cda01dfe8"
    },
    {
      "key": "shared",
      "url": "https://figma-alpha-api.s3.us-west-2.amazonaws.com/images/bd947d4f-62b7-4a40-afa4-90d7f8bfe360"
    },
    {
      "key": "skip",
      "url": "https://figma-alpha-api.s3.us-west-2.amazonaws.com/images/892210f9-3ab2-413f-bdf4-69113c794504"
    },
    {
      "key": "spinner",
      "url": "https://figma-alpha-api.s3.us-west-2.amazonaws.com/images/ca29adb0-da97-4ca0-82cf-7f32d4729b8f"
    },
    {
      "key": "stop",
      "url": "https://figma-alpha-api.s3.us-west-2.amazonaws.com/images/34cd36b9-34f1-4534-b3e5-c33f21a5f8d2"
    },
    {
      "key": "tag",
      "url": "https://figma-alpha-api.s3.us-west-2.amazonaws.com/images/01c2c027-a810-4556-b0d6-3bb413d2dd60"
    },
    {
      "key": "team",
      "url": "https://figma-alpha-api.s3.us-west-2.amazonaws.com/images/dc87a3cc-3c8f-4aab-aad7-9b94ded3e9d0"
    },
    {
      "key": "trash",
      "url": "https://figma-alpha-api.s3.us-west-2.amazonaws.com/images/cf256627-498a-48ee-99d2-d9c5b7261a79"
    },
    {
      "key": "wand",
      "url": "https://figma-alpha-api.s3.us-west-2.amazonaws.com/images/c8e300c5-36e5-40a5-ab5a-3e675ca98f91"
    },
    {
      "key": "wikipedia",
      "url": "https://figma-alpha-api.s3.us-west-2.amazonaws.com/images/a296c6c7-dda4-4ea6-b4ae-c6b65cf6da9f"
    },
    {
      "key": "wrong",
      "url": "https://figma-alpha-api.s3.us-west-2.amazonaws.com/images/fcf958ca-aad2-4eac-abab-f326723e35f1"
    },
    {
      "key": "xmark",
      "url": "https://figma-alpha-api.s3.us-west-2.amazonaws.com/images/3f2bfb61-23d1-4e24-bee8-4692c361ded3"
    }
  ]
}